{
  "豆包AI生图": {
    "内心_平静水面": "CZPQbuFzQos9e1xlvx2cmnLAnyh",
    "放下_莲花水面": "BKOFbGqXToqXC5xgFBLc8Irinih",
    "森林_光柱": "TPoMbBnTGofp1ZxYNLTcLKZWnJf",
    "温暖_阳光房间": "SoQnbI3QYoW3UHxx0dWcBwDSnYe",
    "疗愈_双手托举": "OW8nbEPaWoS18axZ0m1cwQzYnFb",
    "禅意_茶与竹": "VY74bVJukoPgcmxhrqjceq2rnbM",
    "童年_窗边光影": "Od4xb0cizo7pHpxVjBRcBwm0n9d",
    "能量_日出": "Oqh1bCjFDoglmpxIsKtcM9opnHc",
    "自然_晨雾山脉": "Nwh3bfansoGZ6UxMkAfcRqpnnde",
    "蜕变_蝴蝶花园": "JU9IbvQIDoGK9SxfZemcP0rDn2b"
  },
  "免费精选图": {
    "山水_晨雾": "KhVib5VmooQJw0xUCXWcV1Sqnuc",
    "日出_金光": "QoZqbMIpsoi453x8BZfcX6oynxb",
    "星空_银河": "TOdqbBnniow30exm6SkcoCbZnLd",
    "树林_绿意": "EXcIbYuhoogcwrx98KhcaL7Jnhh",
    "森林_阳光": "V1RebJsYkoYcdkx0sVAc3UAlnpf",
    "樱花_粉白": "T32cbOVN4obNjhxqcxncx3QunJe",
    "海浪_平静": "NJhtbz1tHo0xyFxF9tEcYMn7nFf",
    "湖面_倒影": "BH11bckiKopPP4x9iYVcswt4nJf",
    "秋叶_金色": "SYrPbDXAoomCg9xXsYSciyRHnIe",
    "竹林_绿光": "Mlu4ba975oTNBgxtSl7cZ58kn3e",
    "花朵_粉色": "HjyTbbqLeoNCFYxJnIJcXUrvnzb",
    "薰衣草_紫色": "VLORbMfTtof4Trxu4vmcwjQyntb",
    "雨后_彩虹": "MUBybYXCOoUgytxdaZ1ci5uhnHe",
    "雪山_蓝天": "QdDmbwHL3oPh02xCMhCc78mZnMg",
    "麦田_黄昏": "JN4lb4p4PoLg7ZxLj8acQoren2e"
  },
  "doc_token": "PFpQdcQ64oR82oxf3LRcZg40nTe",
  "待上传飞书": {
    "能量_女人瑜伽": "（路径: ~/.openclaw/workspace/images/能量_女人瑜伽.jpg）待main账号上传",
    "能量_女人日出山顶": "（路径: ~/.openclaw/workspace/images/能量_女人日出山顶.jpg）待main账号上传",
    "能量_女人冥想": "（路径: ~/.openclaw/workspace/images/能量_女人冥想.jpg）待main账号上传",
    "能量_凤凰火焰": "（路径: ~/.openclaw/workspace/images/能量_凤凰火焰.jpg）待main账号上传"
  }
}